justcleanme/__init__.py
justcleanme/clean_text.py
justcleanme-0.1.0.dist-info/METADATA
justcleanme-0.1.0.dist-info/WHEEL
justcleanme-0.1.0.dist-info/top_level.txt
justcleanme-0.1.0.dist-info/RECORD
