Metadata-Version: 2.1
Name: justcleanme
Version: 0.1.0
Summary: Simple and easy NLP text preprocessing package
Author: Rituraj Pandey
Requires-Python: >=3.6
Requires-Dist: nltk
Requires-Dist: emoji
Requires-Dist: textblob
Requires-Dist: scikit-learn
Requires-Dist: sentence-transformers
